{
  "namespace" : "prismamarket.ee",
  "code" : "klassikaline-kodujuust--440-g",
  "name" : "Klassikaline kodujuust, 440 g",
  "url" : "https://prismamarket.ee/entry/17108/klassikaline-kodujuust--440-g/4740572004353",
  "prices" : [ ],
  "categories" : {
    "16932" : "Milk",
    "products" : "Groceries"
  },
  "details" : {
    "image" : "https://s3-eu-west-1.amazonaws.com/balticsimages/images/180x220/17c460fe005e45a40bc9869eefadcebd.png",
    "ean" : "4740572004353",
    "origin" : "Estonia",
    "ingredients" : "kodujuust, rõõsk koor, sool",
    "brand" : "PIIMAMEISTER OTTO"
  }
}