{
  "namespace" : "barbora.ee",
  "code" : "jogurt-tere-hellus-metsamarjadega-350-g",
  "name" : "Jogurt TERE Hellus metsamarjadega, 350g",
  "url" : "https://barbora.ee/toode/jogurt-tere-hellus-metsamarjadega-350-g",
  "prices" : [ ],
  "categories" : {
    "piimatooted-ja-munad" : "Dairy and eggs",
    "jogurtid-ja-desserdid" : "Yoghurts and desserts"
  },
  "details" : {
    "origin" : "Estonia",
    "description" : "Metsamarjamaitseline Helluse jogurt. Sisaldab Hellus Tartu Ülikooli teadlaste poolt avastatud probiootilisi piimhappebaktereid ME3.",
    "ingredients" : "PIIM, suhkur, paksendaja (tärklis), želatiin, põldmarjad 1,5%, vaarikad 1,2%, mustikad 1,0%, LÕSSIPULBER, pohlad 0,2%, lõhna- ja maitseaine, looduslik lõhna- ja maitseaine, happesuse regulaator (naatriumtsitraatid), vitamiinide segu (A-120 μg, B1 - 0,165 mg, B2 - 0,21 mg, B5 - 0,9 mg, B6 - 0,21 mg, B12 - 0,375 μg, C - 12 mg, D - 0,75 μg, E - 1,8 mg, biotiin - 7,5 μg, foolhape - 30 μg, niatsiin - 2,4 mg)*, juuretis (sisaldab Lactobacillus fermentum ME-3). *15% võrdluskogusest 100 g tootes.",
    "brand" : "HELLUS"
  }
}