{
  "namespace" : "barbora.ee",
  "code" : "koorene-jogurt-farmi-apelsin-sok-400-g",
  "name" : "Koorene jogurt FARMI apelsin&šok., 400g",
  "url" : "https://barbora.ee/toode/koorene-jogurt-farmi-apelsin-sok-400-g",
  "prices" : [ ],
  "categories" : {
    "piimatooted-ja-munad" : "Dairy and eggs",
    "jogurtid-ja-desserdid" : "Yoghurts and desserts"
  },
  "details" : {
    "image" : "https://cdn.barbora.ee/products/df6c2566-1d41-4de1-a511-b10e6df3c662_m.png",
    "origin" : "Estonia",
    "description" : "Koorene jogurt apelsini ja šokolaaditükkidega",
    "ingredients" : "Pastöriseeritud PIIM, suhkur, RÕÕSK KOOR, apelsinid 2,2% šokolaaditükid 0,8% (kakaomass, kakaovõi, suhkur), LÕSSIpulber, modifitseeritud tärklis, paksendajad (želatiin, pektiin, guarkummi), lõhna- ja maitseaine, happesuse regulaatorid (sidrunhape, naatriumtsitraadid), tardaine (kaltsiumtsitraadid), toiduvärv (karoteenid), juuretis.",
    "brand" : "FARMI"
  }
}