{
  "namespace" : "prismamarket.ee",
  "code" : "apelsini-stracciatella-skyr--150-g",
  "name" : "Apelsini-Stracciatella skyr, 150 g",
  "url" : "https://prismamarket.ee/entry/17097/apelsini-stracciatella-skyr--150-g/4740113097011",
  "prices" : [ ],
  "categories" : {
    "16932" : "Milk",
    "products" : "Groceries"
  },
  "details" : {
    "ean" : "4740113097011",
    "origin" : "Estonia",
    "description" : "Spordirahva poolt palavalt armastatud rasvavabade ja naturaalselt kõrge valgusisaldusega Islandilt pärit uus maitse. Pehme ja pisut hapuka maitsega skyr koos hõrgu ning parjalt magusa apelsini-stracciatella lisandiga moodustab täiusliku kombinatsiooni, mis sobib hästi nii hommikusöögiks, valgurikkaks vahepalaks kui tervislikuks desserdiks. X",
    "ingredients" : "piim, suhkur, apelsinid 2,7% šokolaaditükid 1% (kakaomass, kakaovõi, suhkur), modifitseeritud tärklis, paksendajad (pektiin, guarkummi), lõhna- ja maitseaine, happesuse regulaatorid (sidrunhape, naatriumtsitraadid), tardaine (kaltsiumtsitraadid), toiduvärv (karoteenid), juuretis",
    "brand" : "FARMI"
  }
}