{
  "namespace" : "prismamarket.ee",
  "code" : "kirssidega-skyr--150-g",
  "name" : "Kirssidega skyr, 150 g",
  "url" : "https://prismamarket.ee/entry/17097/kirssidega-skyr--150-g/4740113091453",
  "prices" : [ ],
  "categories" : {
    "16932" : "Milk",
    "products" : "Groceries"
  },
  "details" : {
    "ean" : "4740113091453",
    "origin" : "Estonia",
    "ingredients" : "pastöriseeritud rasvatu piim, kirsid 9,4%, suhkur, modifitseeritud tärklis, puu- ja juurvilja kontsentraat (porgand, aroonia, viinamari), paksendajad: pektiin, ksantaankummi, happesuse regulaatorid: sidrunhape, naatriumtsitraadid, kaltsiumtsitraadid; lõhna- ja maitseained, juuretis.",
    "brand" : "FARMI"
  }
}