{
  "namespace" : "prismamarket.ee",
  "code" : "maitsestamata-mahejogurt--250-ml",
  "name" : "Maitsestamata mahejogurt, 250 ml",
  "url" : "https://prismamarket.ee/entry/17097/maitsestamata-mahejogurt--250-ml/4743135000755",
  "prices" : [ ],
  "categories" : {
    "16932" : "Milk",
    "products" : "Groceries"
  },
  "details" : {
    "ean" : "4743135000755",
    "origin" : "Estonia",
    "description" : "Pajumäe mahejogurt on kreemjalt paks, aga sellegipoolest voolava konsistentsiga. Värske maitsega jogurt sobib nii joomiseks kui teiste toitude sisse. See on puhas, naturaalne jogurt, mis on ühteaegu maitsev kui ka tervislik - tegemist on sertifitseeritud mahetootega.",
    "ingredients" : "mahejogurt",
    "brand" : "PAJUMÄE TALU"
  }
}