{
  "namespace" : "prismamarket.ee",
  "code" : "valio-vaarikakissell-magusainetega-1kg",
  "name" : "Valio vaarikakissell magusainetega 1kg",
  "url" : "https://prismamarket.ee/entry/17101/valio-vaarikakissell-magusainetega-1kg/6408430062171",
  "prices" : [ ],
  "categories" : {
    "16932" : "Milk",
    "products" : "Groceries"
  },
  "details" : {
    "image" : "https://s3-eu-west-1.amazonaws.com/balticsimages/images/180x220/912fca42bfec30c74bd54b0ecad87786.png",
    "ean" : "6408430062171",
    "origin" : "Finland",
    "ingredients" : "Vesi, vaarikamahl (10%, kontsentraadist), vaarikad (5%), paksendaja (guarkummi), modifitseeritud maisit채rklis, happesuse regulaator (sidrunhape), toiduv채rv (peedipunane), magusained (aspartaam*, atsesulfaam K). * Sisaldab fen체체lalaniini allikat.",
    "brand" : "VALIO"
  }
}