{
  "namespace" : "prismamarket.ee",
  "code" : "puuviljasalat-arbuus--melon-400-g",
  "name" : "Puuviljasalat arbuus, melon 400 g",
  "url" : "https://prismamarket.ee/entry/16972/puuviljasalat-arbuus--melon-400-g/4742024310074",
  "prices" : [ ],
  "categories" : {
    "16929" : "Fruits and vegetables",
    "products" : "Groceries"
  },
  "details" : {
    "image" : "https://s3-eu-west-1.amazonaws.com/balticsimages/images/180x220/049be54a38d067914e1b72cb28bf39db.png",
    "ean" : "4742024310074",
    "origin" : "Estonia",
    "description" : "Pilt on illustreeriv.",
    "ingredients" : "Arbuus 50%, melon 25%, kantaluup (cantaloupe-melon) 25%"
  }
}