{
  "namespace" : "prismamarket.ee",
  "code" : "viinamari-tume-strawgrape--250-g",
  "name" : "Viinamari tume StrawGrape 250 g",
  "url" : "https://prismamarket.ee/entry/16972/viinamari-tume-strawgrape--250-g/8437013783293",
  "prices" : [ ],
  "categories" : [ {
    "code" : "16929",
    "name" : "Fruits and vegetables",
    "url" : "https://prismamarket.ee/products/16929"
  }, {
    "code" : "products",
    "name" : "Groceries",
    "url" : "https://prismamarket.ee/products/selection"
  } ]
}