{
  "namespace" : "barbora.ee",
  "code" : "kreeka-jogurt-alma-mango-180-g",
  "name" : "Kreeka jogurt ALMA mango,180g",
  "url" : "https://barbora.ee/toode/kreeka-jogurt-alma-mango-180-g",
  "prices" : [ ],
  "categories" : {
    "piimatooted-ja-munad" : "Dairy and eggs",
    "jogurtid-ja-desserdid" : "Yoghurts and desserts"
  },
  "details" : {
    "origin" : "Estonia",
    "description" : "Mangomaitseline kreeka stiilis jogurt puuviljadest suhkrutega",
    "ingredients" : "PIIM, KOOR, 천unamahla kontsentraat 11,2%, mango 10%, modifitseeritud t채rklis, l천hna- ja maitseaine, paksendaja (pektiinid), happesuse regulaatorid (sidrunhape, naatriumtsitraadid), tardaine (kaltsiumtsitraadid), toiduv채rv (karoteenid), juuretis",
    "brand" : "ALMA"
  }
}