{
  "namespace" : "barbora.ee",
  "code" : "aedkannike-voorasema-rasberry-xp",
  "name" : "Aedkannike (võõrasema) Rasberry XP",
  "url" : "https://barbora.ee/toode/aedkannike-voorasema-rasberry-xp",
  "prices" : [ ],
  "categories" : {
    "aiakaubad" : "Gardening",
    "kodukaubad-ja-vaba-aeg" : "Home and leisure"
  },
  "details" : {
    "origin" : "Lithuania",
    "description" : "Aedkannike on varakevadel õitsev, 10-15 cm kõrgune lill. Kasvatatakse kaheaastasena. Õie läbimõõt 3,7-7 cm, erikujuline. Kõige paremini kasvab päikeselises või poolvarjulises kohas."
  }
}