{
  "namespace" : "barbora.ee",
  "code" : "porgand-fidra",
  "name" : "Porgand Fidra",
  "url" : "https://barbora.ee/toode/porgand-fidra",
  "prices" : [ ],
  "categories" : {
    "aiakaubad" : "Gardening",
    "kodukaubad-ja-vaba-aeg" : "Home and leisure"
  },
  "details" : {
    "image" : "https://cdn.barbora.ee/products/ac451cee-468f-405b-aaa4-6126f1588c54_m.png",
    "origin" : "Lithuania",
    "description" : "Hiline porgandisort, viljakas, säilitamisel säilib hästi. Sobib pesemiseks ja pakendamiseks, vegetatsiooniperiood 110-120 päeva. Juurikad on silindrikujulised, ereoranži värvi. Sobib mehhaaniliseks koristamiseks."
  }
}